backlink_checker/__init__.py
backlink_checker-0.0.6.dist-info/LICENSE
backlink_checker-0.0.6.dist-info/METADATA
backlink_checker-0.0.6.dist-info/WHEEL
backlink_checker-0.0.6.dist-info/top_level.txt
backlink_checker-0.0.6.dist-info/RECORD
